Workbook

Sheet ⚙ Configurações
A1: EQUILIBRIUM — CONFIGURAÇÕES FINANCEIRAS (preencha as células azuis)
A2: Valores são usados automaticamente em todas as abas
A4: A · VALOR RECEBIDO POR SESSÃO (R$) — por convênio
A5: 1 | B5: Ndi Minas | C5: 160 | D5: ← Valor que o convênio paga por sessão
A6: 2 | B6: Unimed | C6: 180 | D6: ← Valor que o convênio paga por sessão
A7: 3 | B7: Particular | C7: 350 | D7: ← Valor que o convênio paga por sessão
A8: 4 | B8: Geap | C8: 160 | D8: ← Valor que o convênio paga por sessão
A9: 5 | B9: Hapvida | C9: 140 | D9: ← Valor que o convênio paga por sessão
A10: 6 | B10: Usisaude | C10: 140 | D10: ← Valor que o convênio paga por sessão
A13: B · VALOR WESSILON — por procedimento + convênio
A14: # | B14: Procedimento | C14: Ndi Minas | D14: Unimed | E14: Particular | F14: Geap | G14: Hapvida | H14: Usisaude
A15: 1 | B15: Anamnese | C15: 160 | D15: 180 | E15: 320 | F15: 160 | G15: 140 | H15: 140
A16: 2 | B16: Devolutiva | C16: 160 | D16: 180 | E16: 320 | F16: 160 | G16: 140 | H16: 140
A17: 3 | B17: Psicoterapia | C17: 0 | D17: 0 | E17: 220 | F17: 0 | G17: 0 | H17: 0
A18: 4 | B18: Avaliação | C18: 160 | D18: 180 | E18: 350 | F18: 160 | G18: 140 | H18: 140
A21: C · REMUNERAÇÃO DOS PROFISSIONAIS DE TESTES
A22: # | B22: Profissional | C22: Tipo | D22: % ou R$/Sessão | E22: Obs.
A23: 1 | B23: Emily Ferreira | C23: pct | D23: 0.4 | E23: % do valor do convênio por sessão
A24: 2 | B24: Karolina Oliveira | C24: pct | D24: 0.4 | E24: % do valor do convênio por sessão
A25: 3 | B25: Mariana Pereira | C25: pct | D25: 0.4 | E25: % do valor do convênio por sessão
A26: 4 | B26: Pâmela Dutra | C26: pct | D26: 0.4 | E26: % do valor do convênio por sessão
A27: 5 | B27: Taís Souza | C27: pct | D27: 0.4 | E27: % do valor do convênio por sessão
A28: 6 | B28: Wessilon Marques | C28: prolabore | D28: 0 | E28: Pró-labore — ver Wessilon
A31: LEGENDA
B32: Célula azul = entrada (você deve preencher)
B33: Célula preta = fórmula (calculado automaticamente)
B34: Célula verde = resultado positivo
B35: Célula vermelha = atenção / custo elevado

Sheet 🧪 Testes por Profissional
A1: TESTES — SESSÕES REALIZADAS, RECEITA E PAGAMENTO POR PROFISSIONAL
C2: Ndi Minas | G2: Unimed | K2: Particular | O2: Geap | S2: Hapvida | W2: Usisaude | AA2: Total Sess. | AB2: Receita Total | AC2: Custo Profis. | AD2: Margem Líquida
C3: Fev | D3: Mar | E3: Receita Total | F3: Custo Prof. | G3: Fev | H3: Mar | I3: Receita Total | J3: Custo Prof. | K3: Fev | L3: Mar | M3: Receita Total | N3: Custo Prof. | O3: Fev | P3: Mar | Q3: Receita Total | R3: Custo Prof. | S3: Fev | T3: Mar | U3: Receita Total | V3: Custo Prof. | W3: Fev | X3: Mar | Y3: Receita Total | Z3: Custo Prof. | AA3: Total Sess. | AB3: Receita Total | AC3: Custo Profis. | AD3: Margem Líquida
A4: Emily Ferreira | B4: 1 | C4: 39 | D4: 39 | E4: =(C4+D4)*'⚙ Configurações'!C5 -> 12480 | F4: =E4*'⚙ Configurações'!D23 -> 4992 | G4: 45 | H4: 69 | I4: =(G4+H4)*'⚙ Configurações'!C6 -> 20520 | J4: =I4*'⚙ Configurações'!D23 -> 8208 | K4: 7 | L4: 2 | M4: =(K4+L4)*'⚙ Configurações'!C7 -> 3150 | N4: =M4*'⚙ Configurações'!D23 -> 1260 | O4: 0 | P4: 5 | Q4: =(O4+P4)*'⚙ Configurações'!C8 -> 800 | R4: =Q4*'⚙ Configurações'!D23 -> 320 | S4: 0 | T4: 4 | U4: =(S4+T4)*'⚙ Configurações'!C9 -> 560 | V4: =U4*'⚙ Configurações'!D23 -> 224 | W4: 0 | X4: 1 | Y4: =(W4+X4)*'⚙ Configurações'!C10 -> 140 | Z4: =Y4*'⚙ Configurações'!D23 -> 56 | AA4: =C4+G4+K4+O4+S4+W4+D4+H4+L4+P4+T4+X4 -> 211 | AB4: =E4+I4+M4+Q4+U4+Y4 -> 37650 | AC4: =F4+J4+N4+R4+V4+Z4 -> 15060 | AD4: =AB4-AC4 -> 22590
A5: Karolina Oliveira | B5: 2 | C5: 55 | D5: 46 | E5: =(C5+D5)*'⚙ Configurações'!C5 -> 16160 | F5: =E5*'⚙ Configurações'!D24 -> 6464 | G5: 20 | H5: 41 | I5: =(G5+H5)*'⚙ Configurações'!C6 -> 10980 | J5: =I5*'⚙ Configurações'!D24 -> 4392 | K5: 0 | L5: 0 | M5: =(K5+L5)*'⚙ Configurações'!C7 -> 0 | N5: =M5*'⚙ Configurações'!D24 -> 0 | O5: 1 | P5: 8 | Q5: =(O5+P5)*'⚙ Configurações'!C8 -> 1440 | R5: =Q5*'⚙ Configurações'!D24 -> 576 | S5: 0 | T5: 0 | U5: =(S5+T5)*'⚙ Configurações'!C9 -> 0 | V5: =U5*'⚙ Configurações'!D24 -> 0 | W5: 0 | X5: 0 | Y5: =(W5+X5)*'⚙ Configurações'!C10 -> 0 | Z5: =Y5*'⚙ Configurações'!D24 -> 0 | AA5: =C5+G5+K5+O5+S5+W5+D5+H5+L5+P5+T5+X5 -> 171 | AB5: =E5+I5+M5+Q5+U5+Y5 -> 28580 | AC5: =F5+J5+N5+R5+V5+Z5 -> 11432 | AD5: =AB5-AC5 -> 17148
A6: Mariana Pereira | B6: 3 | C6: 21 | D6: 23 | E6: =(C6+D6)*'⚙ Configurações'!C5 -> 7040 | F6: =E6*'⚙ Configurações'!D25 -> 2816 | G6: 26 | H6: 34 | I6: =(G6+H6)*'⚙ Configurações'!C6 -> 10800 | J6: =I6*'⚙ Configurações'!D25 -> 4320 | K6: 0 | L6: 0 | M6: =(K6+L6)*'⚙ Configurações'!C7 -> 0 | N6: =M6*'⚙ Configurações'!D25 -> 0 | O6: 0 | P6: 5 | Q6: =(O6+P6)*'⚙ Configurações'!C8 -> 800 | R6: =Q6*'⚙ Configurações'!D25 -> 320 | S6: 0 | T6: 0 | U6: =(S6+T6)*'⚙ Configurações'!C9 -> 0 | V6: =U6*'⚙ Configurações'!D25 -> 0 | W6: 0 | X6: 0 | Y6: =(W6+X6)*'⚙ Configurações'!C10 -> 0 | Z6: =Y6*'⚙ Configurações'!D25 -> 0 | AA6: =C6+G6+K6+O6+S6+W6+D6+H6+L6+P6+T6+X6 -> 109 | AB6: =E6+I6+M6+Q6+U6+Y6 -> 18640 | AC6: =F6+J6+N6+R6+V6+Z6 -> 7456 | AD6: =AB6-AC6 -> 11184
A7: Pâmela Dutra | B7: 4 | C7: 22 | D7: 43 | E7: =(C7+D7)*'⚙ Configurações'!C5 -> 10400 | F7: =E7*'⚙ Configurações'!D26 -> 4160 | G7: 59 | H7: 79 | I7: =(G7+H7)*'⚙ Configurações'!C6 -> 24840 | J7: =I7*'⚙ Configurações'!D26 -> 9936 | K7: 20 | L7: 13 | M7: =(K7+L7)*'⚙ Configurações'!C7 -> 11550 | N7: =M7*'⚙ Configurações'!D26 -> 4620 | O7: 0 | P7: 0 | Q7: =(O7+P7)*'⚙ Configurações'!C8 -> 0 | R7: =Q7*'⚙ Configurações'!D26 -> 0 | S7: 0 | T7: 0 | U7: =(S7+T7)*'⚙ Configurações'!C9 -> 0 | V7: =U7*'⚙ Configurações'!D26 -> 0 | W7: 0 | X7: 0 | Y7: =(W7+X7)*'⚙ Configurações'!C10 -> 0 | Z7: =Y7*'⚙ Configurações'!D26 -> 0 | AA7: =C7+G7+K7+O7+S7+W7+D7+H7+L7+P7+T7+X7 -> 236 | AB7: =E7+I7+M7+Q7+U7+Y7 -> 46790 | AC7: =F7+J7+N7+R7+V7+Z7 -> 18716 | AD7: =AB7-AC7 -> 28074
A8: Taís Souza | B8: 5 | C8: 40 | D8: 28 | E8: =(C8+D8)*'⚙ Configurações'!C5 -> 10880 | F8: =E8*'⚙ Configurações'!D27 -> 4352 | G8: 41 | H8: 89 | I8: =(G8+H8)*'⚙ Configurações'!C6 -> 23400 | J8: =I8*'⚙ Configurações'!D27 -> 9360 | K8: 0 | L8: 5 | M8: =(K8+L8)*'⚙ Configurações'!C7 -> 1750 | N8: =M8*'⚙ Configurações'!D27 -> 700 | O8: 0 | P8: 0 | Q8: =(O8+P8)*'⚙ Configurações'!C8 -> 0 | R8: =Q8*'⚙ Configurações'!D27 -> 0 | S8: 0 | T8: 0 | U8: =(S8+T8)*'⚙ Configurações'!C9 -> 0 | V8: =U8*'⚙ Configurações'!D27 -> 0 | W8: 0 | X8: 0 | Y8: =(W8+X8)*'⚙ Configurações'!C10 -> 0 | Z8: =Y8*'⚙ Configurações'!D27 -> 0 | AA8: =C8+G8+K8+O8+S8+W8+D8+H8+L8+P8+T8+X8 -> 203 | AB8: =E8+I8+M8+Q8+U8+Y8 -> 36030 | AC8: =F8+J8+N8+R8+V8+Z8 -> 14412 | AD8: =AB8-AC8 -> 21618
A9: Wessilon Marques | B9: 6 | C9: 0 | D9: 0 | E9: =(C9+D9)*'⚙ Configurações'!C5 -> 0 | F9: 0 | G9: 0 | H9: 0 | I9: =(G9+H9)*'⚙ Configurações'!C6 -> 0 | J9: 0 | K9: 0 | L9: 4 | M9: =(K9+L9)*'⚙ Configurações'!C7 -> 1400 | N9: 0 | O9: 0 | P9: 0 | Q9: =(O9+P9)*'⚙ Configurações'!C8 -> 0 | R9: 0 | S9: 0 | T9: 0 | U9: =(S9+T9)*'⚙ Configurações'!C9 -> 0 | V9: 0 | W9: 0 | X9: 0 | Y9: =(W9+X9)*'⚙ Configurações'!C10 -> 0 | Z9: 0 | AA9: =C9+G9+K9+O9+S9+W9+D9+H9+L9+P9+T9+X9 -> 4 | AB9: =E9+I9+M9+Q9+U9+Y9 -> 1400 | AC9: =F9+J9+N9+R9+V9+Z9 -> 0 | AD9: =AB9-AC9 -> 1400
A10: TOTAL CLÍNICA | C10: =SUM(C4:C9) -> 177 | D10: =SUM(D4:D9) -> 179 | E10: =SUM(E4:E9) -> 56960 | F10: =SUM(F4:F9) -> 22784 | G10: =SUM(G4:G9) -> 191 | H10: =SUM(H4:H9) -> 312 | I10: =SUM(I4:I9) -> 90540 | J10: =SUM(J4:J9) -> 36216 | ... AD10: =SUM(AD4:AD9) -> 102014

Sheet 👨‍⚕️ Wessilon
A1: WESSILON — ANAMNESES, DEVOLUTIVAS E SESSÕES POR CONVÊNIO
B2: Ndi Minas | F2: Unimed | J2: Particular | N2: Geap | R2: Hapvida | V2: Usisaude | Z2: Total Sess. | AA2: Receita Total
B3: Fev | C3: Mar | D3: Receita Total | E3: Valor/Sessão | F3: Fev | G3: Mar | H3: Receita Total | I3: Valor/Sessão | J3: Fev | K3: Mar | L3: Receita Total | M3: Valor/Sessão | N3: Fev | O3: Mar | P3: Receita Total | Q3: Valor/Sessão | R3: Fev | S3: Mar | T3: Receita Total | U3: Valor/Sessão | V3: Fev | W3: Mar | X3: Receita Total | Y3: Valor/Sessão | Z3: Total Sess. | AA3: Receita Total
A4: Anamnese | B4: 40 | C4: 31 | D4: =(B4+C4)*'⚙ Configurações'!C15 -> 11360 | E4: ='⚙ Configurações'!C15 -> 160 | F4: 84 | G4: 49 | H4: =(F4+G4)*'⚙ Configurações'!D15 -> 23940 | I4: ='⚙ Configurações'!D15 -> 180 | J4: 4 | K4: 3 | L4: =(J4+K4)*'⚙ Configurações'!E15 -> 2240 | M4: ='⚙ Configurações'!E15 -> 320 | N4: 4 | O4: 2 | P4: =(N4+O4)*'⚙ Configurações'!F15 -> 960 | Q4: ='⚙ Configurações'!F15 -> 160 | R4: 0 | S4: 1 | T4: =(R4+S4)*'⚙ Configurações'!G15 -> 140 | U4: ='⚙ Configurações'!G15 -> 140 | V4: 0 | W4: 1 | X4: =(V4+W4)*'⚙ Configurações'!H15 -> 140 | Y4: ='⚙ Configurações'!H15 -> 140 | Z4: =B4+F4+J4+N4+R4+V4+C4+G4+K4+O4+S4+W4 -> 219 | AA4: =D4+H4+L4+P4+T4+X4 -> 38780
A5: Devolutiva | B5: 48 | C5: 29 | D5: =(B5+C5)*'⚙ Configurações'!C16 -> 12320 | E5: ='⚙ Configurações'!C16 -> 160 | F5: 36 | G5: 25 | H5: =(F5+G5)*'⚙ Configurações'!D16 -> 10980 | I5: ='⚙ Configurações'!D16 -> 180 | J5: 4 | K5: 3 | L5: =(J5+K5)*'⚙ Configurações'!E16 -> 2240 | M5: ='⚙ Configurações'!E16 -> 320 | N5: 0 | O5: 0 | P5: =(N5+O5)*'⚙ Configurações'!F16 -> 0 | Q5: ='⚙ Configurações'!F16 -> 160 | R5: 0 | S5: 0 | T5: =(R5+S5)*'⚙ Configurações'!G16 -> 0 | U5: ='⚙ Configurações'!G16 -> 140 | V5: 0 | W5: 0 | X5: =(V5+W5)*'⚙ Configurações'!H16 -> 0 | Y5: ='⚙ Configurações'!H16 -> 140 | Z5: =B5+F5+J5+N5+R5+V5+C5+G5+K5+O5+S5+W5 -> 145 | AA5: =D5+H5+L5+P5+T5+X5 -> 25540
A6: Psicoterapia | B6: 0 | C6: 0 | D6: =(B6+C6)*'⚙ Configurações'!C17 -> 0 | E6: ='⚙ Configurações'!C17 -> 0 | F6: 0 | G6: 0 | H6: =(F6+G6)*'⚙ Configurações'!D17 -> 0 | I6: ='⚙ Configurações'!D17 -> 0 | J6: 10 | K6: 5 | L6: =(J6+K6)*'⚙ Configurações'!E17 -> 3300 | M6: ='⚙ Configurações'!E17 -> 220 | N6: 0 | O6: 0 | P6: =(N6+O6)*'⚙ Configurações'!F17 -> 0 | Q6: ='⚙ Configurações'!F17 -> 0 | R6: 0 | S6: 0 | T6: =(R6+S6)*'⚙ Configurações'!G17 -> 0 | U6: ='⚙ Configurações'!G17 -> 0 | V6: 0 | W6: 0 | X6: =(V6+W6)*'⚙ Configurações'!H17 -> 0 | Y6: ='⚙ Configurações'!H17 -> 0 | Z6: =B6+F6+J6+N6+R6+V6+C6+G6+K6+O6+S6+W6 -> 15 | AA6: =D6+H6+L6+P6+T6+X6 -> 3300
A7: Avaliação | B7: 0 | C7: 0 | D7: =(B7+C7)*'⚙ Configurações'!C18 -> 0 | E7: ='⚙ Configurações'!C18 -> 160 | F7: 0 | G7: 0 | H7: =(F7+G7)*'⚙ Configurações'!D18 -> 0 | I7: ='⚙ Configurações'!D18 -> 180 | J7: 0 | K7: 4 | L7: =(J7+K7)*'⚙ Configurações'!E18 -> 1400 | M7: ='⚙ Configurações'!E18 -> 350 | N7: 0 | O7: 0 | P7: =(N7+O7)*'⚙ Configurações'!F18 -> 0 | Q7: ='⚙ Configurações'!F18 -> 160 | R7: 0 | S7: 0 | T7: =(R7+S7)*'⚙ Configurações'!G18 -> 0 | U7: ='⚙ Configurações'!G18 -> 140 | V7: 0 | W7: 0 | X7: =(V7+W7)*'⚙ Configurações'!H18 -> 0 | Y7: ='⚙ Configurações'!H18 -> 140 | Z7: =B7+F7+J7+N7+R7+V7+C7+G7+K7+O7+S7+W7 -> 4 | AA7: =D7+H7+L7+P7+T7+X7 -> 1400
A8: TOTAL | B8: =SUM(B4:B7) -> 88 | C8: =SUM(C4:C7) -> 60 | D8: =SUM(D4:D7) -> 23680 | F8: =SUM(F4:F7) -> 120 | G8: =SUM(G4:G7) -> 74 | H8: =SUM(H4:H7) -> 34920 | J8: =SUM(J4:J7) -> 18 | K8: =SUM(K4:K7) -> 15 | L8: =SUM(L4:L7) -> 9180 | N8: =SUM(N4:N7) -> 4 | O8: =SUM(O4:O7) -> 2 | P8: =SUM(P4:P7) -> 960 | R8: =SUM(R4:R7) -> 0 | S8: =SUM(S4:S7) -> 1 | T8: =SUM(T4:T7) -> 140 | V8: =SUM(V4:V7) -> 0 | W8: =SUM(W4:W7) -> 1 | X8: =SUM(X4:X7) -> 140 | Z8: =SUM(Z4:Z7) -> 383 | AA8: =SUM(AA4:AA7) -> 69020

Sheet 📊 Resumo por Convênio
A1: RESUMO FINANCEIRO — RECEITA E CUSTO POR CONVÊNIO
A2: Convênio | B2: Sess. Testes | C2: Sess. Wessilon | D2: Total Sessões | E2: Receita Testes | F2: Receita Wessilon | G2: Receita Total | H2: Custo Profis. | I2: Margem Clínica | J2: Margem %
A3: Ndi Minas | B3: =SUM('🧪 Testes por Profissional'!C4:C9)+SUM('🧪 Testes por Profissional'!D4:D9) -> 356 | C3: =('👨‍⚕️ Wessilon'!B4+'👨‍⚕️ Wessilon'!C4)+('👨‍⚕️ Wessilon'!B5+'👨‍⚕️ Wessilon'!C5)+('👨‍⚕️ Wessilon'!B6+'👨‍⚕️ Wessilon'!C6)+('👨‍⚕️ Wessilon'!B7+'👨‍⚕️ Wessilon'!C7) -> 148 | D3: =B3+C3 -> 504 | E3: ='🧪 Testes por Profissional'!E4+'🧪 Testes por Profissional'!E5+'🧪 Testes por Profissional'!E6+'🧪 Testes por Profissional'!E7+'🧪 Testes por Profissional'!E8+'🧪 Testes por Profissional'!E9 -> 56960 | F3: ='👨‍⚕️ Wessilon'!D4+'👨‍⚕️ Wessilon'!D5+'👨‍⚕️ Wessilon'!D6+'👨‍⚕️ Wessilon'!D7 -> 23680 | G3: =E3+F3 -> 80640 | H3: ='🧪 Testes por Profissional'!F4+'🧪 Testes por Profissional'!F5+'🧪 Testes por Profissional'!F6+'🧪 Testes por Profissional'!F7+'🧪 Testes por Profissional'!F8+'🧪 Testes por Profissional'!F9 -> 22784 | I3: =G3-H3 -> 57856 | J3: =IFERROR(I3/G3,0) -> 0.71746032
A4: Unimed | B4: =SUM('🧪 Testes por Profissional'!G4:G9)+SUM('🧪 Testes por Profissional'!H4:H9) -> 503 | C4: =('👨‍⚕️ Wessilon'!F4+'👨‍⚕️ Wessilon'!G4)+('👨‍⚕️ Wessilon'!F5+'👨‍⚕️ Wessilon'!G5)+('👨‍⚕️ Wessilon'!F6+'👨‍⚕️ Wessilon'!G6)+('👨‍⚕️ Wessilon'!F7+'👨‍⚕️ Wessilon'!G7) -> 194 | D4: =B4+C4 -> 697 | E4: ='🧪 Testes por Profissional'!I4+'🧪 Testes por Profissional'!I5+'🧪 Testes por Profissional'!I6+'🧪 Testes por Profissional'!I7+'🧪 Testes por Profissional'!I8+'🧪 Testes por Profissional'!I9 -> 90540 | F4: ='👨‍⚕️ Wessilon'!H4+'👨‍⚕️ Wessilon'!H5+'👨‍⚕️ Wessilon'!H6+'👨‍⚕️ Wessilon'!H7 -> 34920 | G4: =E4+F4 -> 125460 | H4: ='🧪 Testes por Profissional'!J4+'🧪 Testes por Profissional'!J5+'🧪 Testes por Profissional'!J6+'🧪 Testes por Profissional'!J7+'🧪 Testes por Profissional'!J8+'🧪 Testes por Profissional'!J9 -> 36216 | I4: =G4-H4 -> 89244 | J4: =IFERROR(I4/G4,0) -> 0.71133429
A5: Particular | B5: =SUM('🧪 Testes por Profissional'!K4:K9)+SUM('🧪 Testes por Profissional'!L4:L9) -> 51 | C5: =('👨‍⚕️ Wessilon'!J4+'👨‍⚕️ Wessilon'!K4)+('👨‍⚕️ Wessilon'!J5+'👨‍⚕️ Wessilon'!K5)+('👨‍⚕️ Wessilon'!J6+'👨‍⚕️ Wessilon'!K6)+('👨‍⚕️ Wessilon'!J7+'👨‍⚕️ Wessilon'!K7) -> 33 | D5: =B5+C5 -> 84 | E5: ='🧪 Testes por Profissional'!M4+'🧪 Testes por Profissional'!M5+'🧪 Testes por Profissional'!M6+'🧪 Testes por Profissional'!M7+'🧪 Testes por Profissional'!M8+'🧪 Testes por Profissional'!M9 -> 17850 | F5: ='👨‍⚕️ Wessilon'!L4+'👨‍⚕️ Wessilon'!L5+'👨‍⚕️ Wessilon'!L6+'👨‍⚕️ Wessilon'!L7 -> 9180 | G5: =E5+F5 -> 27030 | H5: ='🧪 Testes por Profissional'!N4+'🧪 Testes por Profissional'!N5+'🧪 Testes por Profissional'!N6+'🧪 Testes por Profissional'!N7+'🧪 Testes por Profissional'!N8+'🧪 Testes por Profissional'!N9 -> 6580 | I5: =G5-H5 -> 20450 | J5: =IFERROR(I5/G5,0) -> 0.75656678
A6: Geap | B6: =SUM('🧪 Testes por Profissional'!O4:O9)+SUM('🧪 Testes por Profissional'!P4:P9) -> 19 | C6: =('👨‍⚕️ Wessilon'!N4+'👨‍⚕️ Wessilon'!O4)+('👨‍⚕️ Wessilon'!N5+'👨‍⚕️ Wessilon'!O5)+('👨‍⚕️ Wessilon'!N6+'👨‍⚕️ Wessilon'!O6)+('👨‍⚕️ Wessilon'!N7+'👨‍⚕️ Wessilon'!O7) -> 6 | D6: =B6+C6 -> 25 | E6: ='🧪 Testes por Profissional'!Q4+'🧪 Testes por Profissional'!Q5+'🧪 Testes por Profissional'!Q6+'🧪 Testes por Profissional'!Q7+'🧪 Testes por Profissional'!Q8+'🧪 Testes por Profissional'!Q9 -> 3040 | F6: ='👨‍⚕️ Wessilon'!P4+'👨‍⚕️ Wessilon'!P5+'👨‍⚕️ Wessilon'!P6+'👨‍⚕️ Wessilon'!P7 -> 960 | G6: =E6+F6 -> 4000 | H6: ='🧪 Testes por Profissional'!R4+'🧪 Testes por Profissional'!R5+'🧪 Testes por Profissional'!R6+'🧪 Testes por Profissional'!R7+'🧪 Testes por Profissional'!R8+'🧪 Testes por Profissional'!R9 -> 1216 | I6: =G6-H6 -> 2784 | J6: =IFERROR(I6/G6,0) -> 0.696
A7: Hapvida | B7: =SUM('🧪 Testes por Profissional'!S4:S9)+SUM('🧪 Testes por Profissional'!T4:T9) -> 4 | C7: =('👨‍⚕️ Wessilon'!R4+'👨‍⚕️ Wessilon'!S4)+('👨‍⚕️ Wessilon'!R5+'👨‍⚕️ Wessilon'!S5)+('👨‍⚕️ Wessilon'!R6+'👨‍⚕️ Wessilon'!S6)+('👨‍⚕️ Wessilon'!R7+'👨‍⚕️ Wessilon'!S7) -> 1 | D7: =B7+C7 -> 5 | E7: ='🧪 Testes por Profissional'!U4+'🧪 Testes por Profissional'!U5+'🧪 Testes por Profissional'!U6+'🧪 Testes por Profissional'!U7+'🧪 Testes por Profissional'!U8+'🧪 Testes por Profissional'!U9 -> 560 | F7: ='👨‍⚕️ Wessilon'!T4+'👨‍⚕️ Wessilon'!T5+'👨‍⚕️ Wessilon'!T6+'👨‍⚕️ Wessilon'!T7 -> 140 | G7: =E7+F7 -> 700 | H7: ='🧪 Testes por Profissional'!V4+'🧪 Testes por Profissional'!V5+'🧪 Testes por Profissional'!V6+'🧪 Testes por Profissional'!V7+'🧪 Testes por Profissional'!V8+'🧪 Testes por Profissional'!V9 -> 224 | I7: =G7-H7 -> 476 | J7: =IFERROR(I7/G7,0) -> 0.68
A8: Usisaude | B8: =SUM('🧪 Testes por Profissional'!W4:W9)+SUM('🧪 Testes por Profissional'!X4:X9) -> 1 | C8: =('👨‍⚕️ Wessilon'!V4+'👨‍⚕️ Wessilon'!W4)+('👨‍⚕️ Wessilon'!V5+'👨‍⚕️ Wessilon'!W5)+('👨‍⚕️ Wessilon'!V6+'👨‍⚕️ Wessilon'!W6)+('👨‍⚕️ Wessilon'!V7+'👨‍⚕️ Wessilon'!W7) -> 1 | D8: =B8+C8 -> 2 | E8: ='🧪 Testes por Profissional'!Y4+'🧪 Testes por Profissional'!Y5+'🧪 Testes por Profissional'!Y6+'🧪 Testes por Profissional'!Y7+'🧪 Testes por Profissional'!Y8+'🧪 Testes por Profissional'!Y9 -> 140 | F8: ='👨‍⚕️ Wessilon'!X4+'👨‍⚕️ Wessilon'!X5+'👨‍⚕️ Wessilon'!X6+'👨‍⚕️ Wessilon'!X7 -> 140 | G8: =E8+F8 -> 280 | H8: ='🧪 Testes por Profissional'!Z4+'🧪 Testes por Profissional'!Z5+'🧪 Testes por Profissional'!Z6+'🧪 Testes por Profissional'!Z7+'🧪 Testes por Profissional'!Z8+'🧪 Testes por Profissional'!Z9 -> 56 | I8: =G8-H8 -> 224 | J8: =IFERROR(I8/G8,0) -> 0.8
A9: TOTAL GERAL | B9: =SUM(B3:B8) -> 934 | C9: =SUM(C3:C8) -> 383 | D9: =SUM(D3:D8) -> 1317 | E9: =SUM(E3:E8) -> 169090 | F9: =SUM(F3:F8) -> 69020 | G9: =SUM(G3:G8) -> 238110 | H9: =SUM(H3:H8) -> 67076 | I9: =SUM(I3:I8) -> 171034 | J9: =IFERROR(I9/G9,0) -> 0.71829827

Sheet 📅 Fev vs Mar
A1: COMPARATIVO FEVEREIRO vs MARÇO — TESTES E WESSILON
A2: Convênio | B2: Sess Fev | C2: Sess Mar | D2: Δ Sessões | E2: Rec Fev | F2: Rec Mar | G2: Δ Receita | H2: Custo Fev | I2: Custo Mar | J2: Δ Custo
A3: Ndi Minas | B3: ='🧪 Testes por Profissional'!C4+'🧪 Testes por Profissional'!C5+'🧪 Testes por Profissional'!C6+'🧪 Testes por Profissional'!C7+'🧪 Testes por Profissional'!C8+'🧪 Testes por Profissional'!C9+'👨‍⚕️ Wessilon'!B4+'👨‍⚕️ Wessilon'!B5+'👨‍⚕️ Wessilon'!B6+'👨‍⚕️ Wessilon'!B7 -> 265 | C3: ='🧪 Testes por Profissional'!D4+'🧪 Testes por Profissional'!D5+'🧪 Testes por Profissional'!D6+'🧪 Testes por Profissional'!D7+'🧪 Testes por Profissional'!D8+'🧪 Testes por Profissional'!D9+'👨‍⚕️ Wessilon'!C4+'👨‍⚕️ Wessilon'!C5+'👨‍⚕️ Wessilon'!C6+'👨‍⚕️ Wessilon'!C7 -> 239 | D3: =C3-B3 -> -26 | E3: =B3*'⚙ Configurações'!C5 -> 42400 | F3: =C3*'⚙ Configurações'!C5 -> 38240 | G3: =F3-E3 -> -4160 | H3: ='🧪 Testes por Profissional'!C4*'⚙ Configurações'!C5*'⚙ Configurações'!D23+'🧪 Testes por Profissional'!C5*'⚙ Configurações'!C5*'⚙ Configurações'!D24+'🧪 Testes por Profissional'!C6*'⚙ Configurações'!C5*'⚙ Configurações'!D25+'🧪 Testes por Profissional'!C7*'⚙ Configurações'!C5*'⚙ Configurações'!D26+'🧪 Testes por Profissional'!C8*'⚙ Configurações'!C5*'⚙ Configurações'!D27 -> 11328 | I3: ='🧪 Testes por Profissional'!D4*'⚙ Configurações'!C5*'⚙ Configurações'!D23+'🧪 Testes por Profissional'!D5*'⚙ Configurações'!C5*'⚙ Configurações'!D24+'🧪 Testes por Profissional'!D6*'⚙ Configurações'!C5*'⚙ Configurações'!D25+'🧪 Testes por Profissional'!D7*'⚙ Configurações'!C5*'⚙ Configurações'!D26+'🧪 Testes por Profissional'!D8*'⚙ Configurações'!C5*'⚙ Configurações'!D27 -> 11456 | J3: =I3-H3 -> 128
A4: Unimed | B4: ='🧪 Testes por Profissional'!G4+'🧪 Testes por Profissional'!G5+'🧪 Testes por Profissional'!G6+'🧪 Testes por Profissional'!G7+'🧪 Testes por Profissional'!G8+'🧪 Testes por Profissional'!G9+'👨‍⚕️ Wessilon'!F4+'👨‍⚕️ Wessilon'!F5+'👨‍⚕️ Wessilon'!F6+'👨‍⚕️ Wessilon'!F7 -> 311 | C4: ='🧪 Testes por Profissional'!H4+'🧪 Testes por Profissional'!H5+'🧪 Testes por Profissional'!H6+'🧪 Testes por Profissional'!H7+'🧪 Testes por Profissional'!H8+'🧪 Testes por Profissional'!H9+'👨‍⚕️ Wessilon'!G4+'👨‍⚕️ Wessilon'!G5+'👨‍⚕️ Wessilon'!G6+'👨‍⚕️ Wessilon'!G7 -> 386 | D4: =C4-B4 -> 75 | E4: =B4*'⚙ Configurações'!C6 -> 55980 | F4: =C4*'⚙ Configurações'!C6 -> 69480 | G4: =F4-E4 -> 13500 | H4: ='🧪 Testes por Profissional'!G4*'⚙ Configurações'!C6*'⚙ Configurações'!D23+'🧪 Testes por Profissional'!G5*'⚙ Configurações'!C6*'⚙ Configurações'!D24+'🧪 Testes por Profissional'!G6*'⚙ Configurações'!C6*'⚙ Configurações'!D25+'🧪 Testes por Profissional'!G7*'⚙ Configurações'!C6*'⚙ Configurações'!D26+'🧪 Testes por Profissional'!G8*'⚙ Configurações'!C6*'⚙ Configurações'!D27 -> 13752 | I4: ='🧪 Testes por Profissional'!H4*'⚙ Configurações'!C6*'⚙ Configurações'!D23+'🧪 Testes por Profissional'!H5*'⚙ Configurações'!C6*'⚙ Configurações'!D24+'🧪 Testes por Profissional'!H6*'⚙ Configurações'!C6*'⚙ Configurações'!D25+'🧪 Testes por Profissional'!H7*'⚙ Configurações'!C6*'⚙ Configurações'!D26+'🧪 Testes por Profissional'!H8*'⚙ Configurações'!C6*'⚙ Configurações'!D27 -> 22464 | J4: =I4-H4 -> 8712
A5: Particular | B5: ='🧪 Testes por Profissional'!K4+'🧪 Testes por Profissional'!K5+'🧪 Testes por Profissional'!K6+'🧪 Testes por Profissional'!K7+'🧪 Testes por Profissional'!K8+'🧪 Testes por Profissional'!K9+'👨‍⚕️ Wessilon'!J4+'👨‍⚕️ Wessilon'!J5+'👨‍⚕️ Wessilon'!J6+'👨‍⚕️ Wessilon'!J7 -> 45 | C5: ='🧪 Testes por Profissional'!L4+'🧪 Testes por Profissional'!L5+'🧪 Testes por Profissional'!L6+'🧪 Testes por Profissional'!L7+'🧪 Testes por Profissional'!L8+'🧪 Testes por Profissional'!L9+'👨‍⚕️ Wessilon'!K4+'👨‍⚕️ Wessilon'!K5+'👨‍⚕️ Wessilon'!K6+'👨‍⚕️ Wessilon'!K7 -> 39 | D5: =C5-B5 -> -6 | E5: =B5*'⚙ Configurações'!C7 -> 15750 | F5: =C5*'⚙ Configurações'!C7 -> 13650 | G5: =F5-E5 -> -2100 | H5: ='🧪 Testes por Profissional'!K4*'⚙ Configurações'!C7*'⚙ Configurações'!D23+'🧪 Testes por Profissional'!K5*'⚙ Configurações'!C7*'⚙ Configurações'!D24+'🧪 Testes por Profissional'!K6*'⚙ Configurações'!C7*'⚙ Configurações'!D25+'🧪 Testes por Profissional'!K7*'⚙ Configurações'!C7*'⚙ Configurações'!D26+'🧪 Testes por Profissional'!K8*'⚙ Configurações'!C7*'⚙ Configurações'!D27 -> 3780 | I5: ='🧪 Testes por Profissional'!L4*'⚙ Configurações'!C7*'⚙ Configurações'!D23+'🧪 Testes por Profissional'!L5*'⚙ Configurações'!C7*'⚙ Configurações'!D24+'🧪 Testes por Profissional'!L6*'⚙ Configurações'!C7*'⚙ Configurações'!D25+'🧪 Testes por Profissional'!L7*'⚙ Configurações'!C7*'⚙ Configurações'!D26+'🧪 Testes por Profissional'!L8*'⚙ Configurações'!C7*'⚙ Configurações'!D27 -> 2800 | J5: =I5-H5 -> -980
A6: Geap | B6: ='🧪 Testes por Profissional'!O4+'🧪 Testes por Profissional'!O5+'🧪 Testes por Profissional'!O6+'🧪 Testes por Profissional'!O7+'🧪 Testes por Profissional'!O8+'🧪 Testes por Profissional'!O9+'👨‍⚕️ Wessilon'!N4+'👨‍⚕️ Wessilon'!N5+'👨‍⚕️ Wessilon'!N6+'👨‍⚕️ Wessilon'!N7 -> 5 | C6: ='🧪 Testes por Profissional'!P4+'🧪 Testes por Profissional'!P5+'🧪 Testes por Profissional'!P6+'🧪 Testes por Profissional'!P7+'🧪 Testes por Profissional'!P8+'🧪 Testes por Profissional'!P9+'👨‍⚕️ Wessilon'!O4+'👨‍⚕️ Wessilon'!O5+'👨‍⚕️ Wessilon'!O6+'👨‍⚕️ Wessilon'!O7 -> 20 | D6: =C6-B6 -> 15 | E6: =B6*'⚙ Configurações'!C8 -> 800 | F6: =C6*'⚙ Configurações'!C8 -> 3200 | G6: =F6-E6 -> 2400 | H6: ='🧪 Testes por Profissional'!O4*'⚙ Configurações'!C8*'⚙ Configurações'!D23+'🧪 Testes por Profissional'!O5*'⚙ Configurações'!C8*'⚙ Configurações'!D24+'🧪 Testes por Profissional'!O6*'⚙ Configurações'!C8*'⚙ Configurações'!D25+'🧪 Testes por Profissional'!O7*'⚙ Configurações'!C8*'⚙ Configurações'!D26+'🧪 Testes por Profissional'!O8*'⚙ Configurações'!C8*'⚙ Configurações'!D27 -> 64 | I6: ='🧪 Testes por Profissional'!P4*'⚙ Configurações'!C8*'⚙ Configurações'!D23+'🧪 Testes por Profissional'!P5*'⚙ Configurações'!C8*'⚙ Configurações'!D24+'🧪 Testes por Profissional'!P6*'⚙ Configurações'!C8*'⚙ Configurações'!D25+'🧪 Testes por Profissional'!P7*'⚙ Configurações'!C8*'⚙ Configurações'!D26+'🧪 Testes por Profissional'!P8*'⚙ Configurações'!C8*'⚙ Configurações'!D27 -> 1152 | J6: =I6-H6 -> 1088
A7: Hapvida | B7: ='🧪 Testes por Profissional'!S4+'🧪 Testes por Profissional'!S5+'🧪 Testes por Profissional'!S6+'🧪 Testes por Profissional'!S7+'🧪 Testes por Profissional'!S8+'🧪 Testes por Profissional'!S9+'👨‍⚕️ Wessilon'!R4+'👨‍⚕️ Wessilon'!R5+'👨‍⚕️ Wessilon'!R6+'👨‍⚕️ Wessilon'!R7 -> 0 | C7: ='🧪 Testes por Profissional'!T4+'🧪 Testes por Profissional'!T5+'🧪 Testes por Profissional'!T6+'🧪 Testes por Profissional'!T7+'🧪 Testes por Profissional'!T8+'🧪 Testes por Profissional'!T9+'👨‍⚕️ Wessilon'!S4+'👨‍⚕️ Wessilon'!S5+'👨‍⚕️ Wessilon'!S6+'👨‍⚕️ Wessilon'!S7 -> 5 | D7: =C7-B7 -> 5 | E7: =B7*'⚙ Configurações'!C9 -> 0 | F7: =C7*'⚙ Configurações'!C9 -> 700 | G7: =F7-E7 -> 700 | H7: ='🧪 Testes por Profissional'!S4*'⚙ Configurações'!C9*'⚙ Configurações'!D23+'🧪 Testes por Profissional'!S5*'⚙ Configurações'!C9*'⚙ Configurações'!D24+'🧪 Testes por Profissional'!S6*'⚙ Configurações'!C9*'⚙ Configurações'!D25+'🧪 Testes por Profissional'!S7*'⚙ Configurações'!C9*'⚙ Configurações'!D26+'🧪 Testes por Profissional'!S8*'⚙ Configurações'!C9*'⚙ Configurações'!D27 -> 0 | I7: ='🧪 Testes por Profissional'!T4*'⚙ Configurações'!C9*'⚙ Configurações'!D23+'🧪 Testes por Profissional'!T5*'⚙ Configurações'!C9*'⚙ Configurações'!D24+'🧪 Testes por Profissional'!T6*'⚙ Configurações'!C9*'⚙ Configurações'!D25+'🧪 Testes por Profissional'!T7*'⚙ Configurações'!C9*'⚙ Configurações'!D26+'🧪 Testes por Profissional'!T8*'⚙ Configurações'!C9*'⚙ Configurações'!D27 -> 224 | J7: =I7-H7 -> 224
A8: Usisaude | B8: ='🧪 Testes por Profissional'!W4+'🧪 Testes por Profissional'!W5+'🧪 Testes por Profissional'!W6+'🧪 Testes por Profissional'!W7+'🧪 Testes por Profissional'!W8+'🧪 Testes por Profissional'!W9+'👨‍⚕️ Wessilon'!V4+'👨‍⚕️ Wessilon'!V5+'👨‍⚕️ Wessilon'!V6+'👨‍⚕️ Wessilon'!V7 -> 0 | C8: ='🧪 Testes por Profissional'!X4+'🧪 Testes por Profissional'!X5+'🧪 Testes por Profissional'!X6+'🧪 Testes por Profissional'!X7+'🧪 Testes por Profissional'!X8+'🧪 Testes por Profissional'!X9+'👨‍⚕️ Wessilon'!W4+'👨‍⚕️ Wessilon'!W5+'👨‍⚕️ Wessilon'!W6+'👨‍⚕️ Wessilon'!W7 -> 2 | D8: =C8-B8 -> 2 | E8: =B8*'⚙ Configurações'!C10 -> 0 | F8: =C8*'⚙ Configurações'!C10 -> 280 | G8: =F8-E8 -> 280 | H8: ='🧪 Testes por Profissional'!W4*'⚙ Configurações'!C10*'⚙ Configurações'!D23+'🧪 Testes por Profissional'!W5*'⚙ Configurações'!C10*'⚙ Configurações'!D24+'🧪 Testes por Profissional'!W6*'⚙ Configurações'!C10*'⚙ Configurações'!D25+'🧪 Testes por Profissional'!W7*'⚙ Configurações'!C10*'⚙ Configurações'!D26+'🧪 Testes por Profissional'!W8*'⚙ Configurações'!C10*'⚙ Configurações'!D27 -> 0 | I8: ='🧪 Testes por Profissional'!X4*'⚙ Configurações'!C10*'⚙ Configurações'!D23+'🧪 Testes por Profissional'!X5*'⚙ Configurações'!C10*'⚙ Configurações'!D24+'🧪 Testes por Profissional'!X6*'⚙ Configurações'!C10*'⚙ Configurações'!D25+'🧪 Testes por Profissional'!X7*'⚙ Configurações'!C10*'⚙ Configurações'!D26+'🧪 Testes por Profissional'!X8*'⚙ Configurações'!C10*'⚙ Configurações'!D27 -> 56 | J8: =I8-H8 -> 56
A9: TOTAL | B9: =SUM(B3:B8) -> 626 | C9: =SUM(C3:C8) -> 691 | D9: =SUM(D3:D8) -> 65 | E9: =SUM(E3:E8) -> 114930 | F9: =SUM(F3:F8) -> 125550 | G9: =SUM(G3:G8) -> 10620 | H9: =SUM(H3:H8) -> 28924 | I9: =SUM(I3:I8) -> 38152 | J9: =SUM(J3:J8) -> 9228
